langchain_crawleo/__init__.py
langchain_crawleo/_utilities.py
langchain_crawleo/crawleo_crawler.py
langchain_crawleo/crawleo_search.py
langchain_crawleo/py.typed
langchain_crawleo-0.1.1.dist-info/licenses/LICENSE
langchain_crawleo-0.1.1.dist-info/METADATA
langchain_crawleo-0.1.1.dist-info/WHEEL
langchain_crawleo-0.1.1.dist-info/RECORD
