Metadata-Version: 2.4
Name: langchain-crawleo
Version: 0.1.1
Summary: An integration package connecting Crawleo (privacy-first search & crawler) and LangChain
License: MIT
License-File: LICENSE
Keywords: langchain,crawleo,search,crawler,web-scraping,privacy
Requires-Python: >=3.10,<4.0
Classifier: License :: OSI Approved :: MIT License
Classifier: Programming Language :: Python :: 3
Classifier: Programming Language :: Python :: 3.10
Classifier: Programming Language :: Python :: 3.11
Classifier: Programming Language :: Python :: 3.12
Classifier: Programming Language :: Python :: 3.13
Classifier: Programming Language :: Python :: 3.14
Requires-Dist: httpx (>=0.27.0)
Requires-Dist: langchain-core (>=0.3.15,<2.0.0)
Requires-Dist: pydantic (>=2.0.0)
Project-URL: Repository, https://github.com/crawleo/langchain-crawleo
